{
"meta":{"test_sets":[],"test_metrics":[],"learn_metrics":[{"best_value":"Min","name":"RMSE"}],"launch_mode":"Train","parameters":"","iteration_count":200,"learn_sets":["learn"],"name":"experiment"},
"iterations":[
{"learn":[3670.596782],"iteration":0,"passed_time":0.01774386343,"remaining_time":3.531028822},
{"learn":[3345.386299],"iteration":1,"passed_time":0.03117352193,"remaining_time":3.086178671},
{"learn":[3048.090717],"iteration":2,"passed_time":0.04451857688,"remaining_time":2.923386548},
{"learn":[2774.655998],"iteration":3,"passed_time":0.05804089699,"remaining_time":2.844003953},
{"learn":[2529.695451],"iteration":4,"passed_time":0.07092184023,"remaining_time":2.765951769},
{"learn":[2315.556654],"iteration":5,"passed_time":0.08377555932,"remaining_time":2.708743085},
{"learn":[2122.419108],"iteration":6,"passed_time":0.09829229961,"remaining_time":2.710059118},
{"learn":[1951.960724],"iteration":7,"passed_time":0.1117514418,"remaining_time":2.682034604},
{"learn":[1795.532243],"iteration":8,"passed_time":0.1259299897,"remaining_time":2.672514225},
{"learn":[1660.385998],"iteration":9,"passed_time":0.142538903,"remaining_time":2.708239157},
{"learn":[1538.35416],"iteration":10,"passed_time":0.1577535062,"remaining_time":2.710492061},
{"learn":[1433.204972],"iteration":11,"passed_time":0.1734874245,"remaining_time":2.717969651},
{"learn":[1336.847229],"iteration":12,"passed_time":0.1901773897,"remaining_time":2.735628606},
{"learn":[1248.830285],"iteration":13,"passed_time":0.204645416,"remaining_time":2.718860527},
{"learn":[1173.405896],"iteration":14,"passed_time":0.2205662323,"remaining_time":2.720316866},
{"learn":[1106.086384],"iteration":15,"passed_time":0.2370621452,"remaining_time":2.72621467},
{"learn":[1044.723014],"iteration":16,"passed_time":0.2531074405,"remaining_time":2.724627154},
{"learn":[992.7088401],"iteration":17,"passed_time":0.2718599766,"remaining_time":2.74880643},
{"learn":[946.0714409],"iteration":18,"passed_time":0.2892033073,"remaining_time":2.755042033},
{"learn":[904.8341283],"iteration":19,"passed_time":0.3059415297,"remaining_time":2.753473768},
{"learn":[870.6768596],"iteration":20,"passed_time":0.3225609018,"remaining_time":2.749447686},
{"learn":[839.1088148],"iteration":21,"passed_time":0.3416806161,"remaining_time":2.764506803},
{"learn":[812.5494468],"iteration":22,"passed_time":0.3570824741,"remaining_time":2.747982518},
{"learn":[788.2158547],"iteration":23,"passed_time":0.3743796992,"remaining_time":2.745451127},
{"learn":[767.4731931],"iteration":24,"passed_time":0.3910632198,"remaining_time":2.737442539},
{"learn":[748.1795416],"iteration":25,"passed_time":0.4061819382,"remaining_time":2.71829451},
{"learn":[732.5468472],"iteration":26,"passed_time":0.4219644058,"remaining_time":2.70369786},
{"learn":[719.4121881],"iteration":27,"passed_time":0.4363485096,"remaining_time":2.680426559},
{"learn":[706.0247615],"iteration":28,"passed_time":0.4520703462,"remaining_time":2.665656179},
{"learn":[694.1349515],"iteration":29,"passed_time":0.4673116875,"remaining_time":2.648099563},
{"learn":[684.4583021],"iteration":30,"passed_time":0.4842994417,"remaining_time":2.640213085},
{"learn":[675.8696298],"iteration":31,"passed_time":0.4998882133,"remaining_time":2.62441312},
{"learn":[668.2783197],"iteration":32,"passed_time":0.5166397391,"remaining_time":2.614510195},
{"learn":[661.7902352],"iteration":33,"passed_time":0.5326488485,"remaining_time":2.600579672},
{"learn":[655.684599],"iteration":34,"passed_time":0.5502505444,"remaining_time":2.594038281},
{"learn":[649.9227334],"iteration":35,"passed_time":0.5674937676,"remaining_time":2.585249386},
{"learn":[645.1480303],"iteration":36,"passed_time":0.5828617587,"remaining_time":2.567742342},
{"learn":[640.6229158],"iteration":37,"passed_time":0.5978013898,"remaining_time":2.548521715},
{"learn":[636.7167845],"iteration":38,"passed_time":0.6129046198,"remaining_time":2.530195995},
{"learn":[633.1210605],"iteration":39,"passed_time":0.6280126289,"remaining_time":2.512050516},
{"learn":[629.4782828],"iteration":40,"passed_time":0.6431910387,"remaining_time":2.494326223},
{"learn":[625.9213998],"iteration":41,"passed_time":0.6575664326,"remaining_time":2.473702294},
{"learn":[623.5074631],"iteration":42,"passed_time":0.6720551049,"remaining_time":2.453782592},
{"learn":[621.1988473],"iteration":43,"passed_time":0.6882049698,"remaining_time":2.439999438},
{"learn":[619.0754325],"iteration":44,"passed_time":0.7019363262,"remaining_time":2.417780679},
{"learn":[616.8370822],"iteration":45,"passed_time":0.7210586446,"remaining_time":2.413978941},
{"learn":[614.9239891],"iteration":46,"passed_time":0.7408208415,"remaining_time":2.411608271},
{"learn":[613.3343575],"iteration":47,"passed_time":0.7557822457,"remaining_time":2.393310445},
{"learn":[611.1784707],"iteration":48,"passed_time":0.7731476732,"remaining_time":2.382557115},
{"learn":[609.6453957],"iteration":49,"passed_time":0.789052329,"remaining_time":2.367156987},
{"learn":[608.08953],"iteration":50,"passed_time":0.8064830562,"remaining_time":2.356195595},
{"learn":[606.9328931],"iteration":51,"passed_time":0.8208433118,"remaining_time":2.336246349},
{"learn":[605.8513573],"iteration":52,"passed_time":0.834555781,"remaining_time":2.314711317},
{"learn":[604.924714],"iteration":53,"passed_time":0.8481600539,"remaining_time":2.293173479},
{"learn":[603.6728554],"iteration":54,"passed_time":0.8621343744,"remaining_time":2.272899714},
{"learn":[602.6041631],"iteration":55,"passed_time":0.878811551,"remaining_time":2.259801131},
{"learn":[601.7455263],"iteration":56,"passed_time":0.8915371276,"remaining_time":2.23666332},
{"learn":[600.9284094],"iteration":57,"passed_time":0.9061507032,"remaining_time":2.218506894},
{"learn":[600.1944545],"iteration":58,"passed_time":0.9193964297,"remaining_time":2.197201637},
{"learn":[599.1853161],"iteration":59,"passed_time":0.9330229484,"remaining_time":2.177053546},
{"learn":[598.5710815],"iteration":60,"passed_time":0.9465775276,"remaining_time":2.15695535},
{"learn":[597.8983369],"iteration":61,"passed_time":0.9602261016,"remaining_time":2.137277452},
{"learn":[597.0937997],"iteration":62,"passed_time":0.9737288063,"remaining_time":2.117473753},
{"learn":[596.5953238],"iteration":63,"passed_time":0.9868196613,"remaining_time":2.09699178},
{"learn":[596.0614181],"iteration":64,"passed_time":0.9983561712,"remaining_time":2.073508971},
{"learn":[594.6108148],"iteration":65,"passed_time":1.010938162,"remaining_time":2.052510814},
{"learn":[593.6114591],"iteration":66,"passed_time":1.022855387,"remaining_time":2.030444277},
{"learn":[592.8264244],"iteration":67,"passed_time":1.03568372,"remaining_time":2.010444867},
{"learn":[592.4062533],"iteration":68,"passed_time":1.046517764,"remaining_time":1.98686706},
{"learn":[591.9345692],"iteration":69,"passed_time":1.059317803,"remaining_time":1.96730449},
{"learn":[591.4104328],"iteration":70,"passed_time":1.072556905,"remaining_time":1.948730151},
{"learn":[590.9292768],"iteration":71,"passed_time":1.084757329,"remaining_time":1.928457474},
{"learn":[590.2316392],"iteration":72,"passed_time":1.097996822,"remaining_time":1.91021365},
{"learn":[589.8493309],"iteration":73,"passed_time":1.110380881,"remaining_time":1.890648526},
{"learn":[589.3710891],"iteration":74,"passed_time":1.12466489,"remaining_time":1.874441484},
{"learn":[589.0923933],"iteration":75,"passed_time":1.136649117,"remaining_time":1.854532769},
{"learn":[588.4797122],"iteration":76,"passed_time":1.149024308,"remaining_time":1.835454414},
{"learn":[587.998666],"iteration":77,"passed_time":1.162134041,"remaining_time":1.817696833},
{"learn":[587.4730943],"iteration":78,"passed_time":1.174348649,"remaining_time":1.798685905},
{"learn":[587.1697069],"iteration":79,"passed_time":1.187116804,"remaining_time":1.780675207},
{"learn":[586.9576207],"iteration":80,"passed_time":1.199566164,"remaining_time":1.7623256},
{"learn":[586.5253074],"iteration":81,"passed_time":1.212539175,"remaining_time":1.744873447},
{"learn":[586.1524325],"iteration":82,"passed_time":1.224748849,"remaining_time":1.726453196},
{"learn":[585.8412403],"iteration":83,"passed_time":1.235932422,"remaining_time":1.706763821},
{"learn":[585.5699345],"iteration":84,"passed_time":1.249098071,"remaining_time":1.689956213},
{"learn":[585.1173248],"iteration":85,"passed_time":1.262463664,"remaining_time":1.673498345},
{"learn":[584.8220126],"iteration":86,"passed_time":1.273511308,"remaining_time":1.654100894},
{"learn":[584.3976013],"iteration":87,"passed_time":1.286452508,"remaining_time":1.637303192},
{"learn":[584.1108147],"iteration":88,"passed_time":1.298029507,"remaining_time":1.618890734},
{"learn":[583.9228906],"iteration":89,"passed_time":1.311966742,"remaining_time":1.603514907},
{"learn":[583.7320265],"iteration":90,"passed_time":1.324784011,"remaining_time":1.5868292},
{"learn":[583.5897342],"iteration":91,"passed_time":1.337958437,"remaining_time":1.570646861},
{"learn":[583.482335],"iteration":92,"passed_time":1.348840444,"remaining_time":1.551891694},
{"learn":[583.2595876],"iteration":93,"passed_time":1.361014041,"remaining_time":1.534760514},
{"learn":[583.1284084],"iteration":94,"passed_time":1.372412155,"remaining_time":1.516876592},
{"learn":[582.7540102],"iteration":95,"passed_time":1.385825193,"remaining_time":1.501310625},
{"learn":[582.5354721],"iteration":96,"passed_time":1.398246,"remaining_time":1.484735443},
{"learn":[582.3276252],"iteration":97,"passed_time":1.410509864,"remaining_time":1.468081695},
{"learn":[582.1497374],"iteration":98,"passed_time":1.424222812,"remaining_time":1.45299499},
{"learn":[581.9577369],"iteration":99,"passed_time":1.437465345,"remaining_time":1.437465345},
{"learn":[581.6501532],"iteration":100,"passed_time":1.44989741,"remaining_time":1.42118657},
{"learn":[581.3562263],"iteration":101,"passed_time":1.461882552,"remaining_time":1.404553825},
{"learn":[581.2758474],"iteration":102,"passed_time":1.474048058,"remaining_time":1.388181181},
{"learn":[581.0613405],"iteration":103,"passed_time":1.485354498,"remaining_time":1.37109646},
{"learn":[580.7824256],"iteration":104,"passed_time":1.495880162,"remaining_time":1.353415385},
{"learn":[580.6031825],"iteration":105,"passed_time":1.508324272,"remaining_time":1.337570581},
{"learn":[580.3605117],"iteration":106,"passed_time":1.520310398,"remaining_time":1.32139128},
{"learn":[580.1932492],"iteration":107,"passed_time":1.533184902,"remaining_time":1.306046398},
{"learn":[579.869671],"iteration":108,"passed_time":1.545794196,"remaining_time":1.29052543},
{"learn":[579.686491],"iteration":109,"passed_time":1.558249766,"remaining_time":1.274931627},
{"learn":[579.5420574],"iteration":110,"passed_time":1.569227751,"remaining_time":1.258209638},
{"learn":[579.3838116],"iteration":111,"passed_time":1.582135545,"remaining_time":1.2431065},
{"learn":[579.1206771],"iteration":112,"passed_time":1.597114023,"remaining_time":1.22963646},
{"learn":[578.7818021],"iteration":113,"passed_time":1.613306037,"remaining_time":1.217055431},
{"learn":[578.5180446],"iteration":114,"passed_time":1.627689813,"remaining_time":1.203075079},
{"learn":[578.4230868],"iteration":115,"passed_time":1.640830842,"remaining_time":1.188187851},
{"learn":[578.2494103],"iteration":116,"passed_time":1.656441108,"remaining_time":1.175082153},
{"learn":[578.160135],"iteration":117,"passed_time":1.669143818,"remaining_time":1.159913501},
{"learn":[577.7076899],"iteration":118,"passed_time":1.684397405,"remaining_time":1.146522604},
{"learn":[577.5758011],"iteration":119,"passed_time":1.698004438,"remaining_time":1.132002958},
{"learn":[577.4291614],"iteration":120,"passed_time":1.70971739,"remaining_time":1.116261767},
{"learn":[577.2850487],"iteration":121,"passed_time":1.723009678,"remaining_time":1.101596352},
{"learn":[577.0296391],"iteration":122,"passed_time":1.737667209,"remaining_time":1.087807928},
{"learn":[576.8524758],"iteration":123,"passed_time":1.750414979,"remaining_time":1.072834987},
{"learn":[576.638409],"iteration":124,"passed_time":1.762508289,"remaining_time":1.057504973},
{"learn":[576.4245279],"iteration":125,"passed_time":1.773818283,"remaining_time":1.041766293},
{"learn":[576.2794308],"iteration":126,"passed_time":1.78667806,"remaining_time":1.026988176},
{"learn":[576.1232994],"iteration":127,"passed_time":1.799295214,"remaining_time":1.012103558},
{"learn":[575.9992666],"iteration":128,"passed_time":1.811072501,"remaining_time":0.9967918417},
{"learn":[575.8549862],"iteration":129,"passed_time":1.822528956,"remaining_time":0.9813617455},
{"learn":[575.7151051],"iteration":130,"passed_time":1.835708053,"remaining_time":0.9668996614},
{"learn":[575.5248648],"iteration":131,"passed_time":1.847662219,"remaining_time":0.9518259917},
{"learn":[575.3626872],"iteration":132,"passed_time":1.859276001,"remaining_time":0.9366277598},
{"learn":[575.2261776],"iteration":133,"passed_time":1.87123345,"remaining_time":0.9216522962},
{"learn":[574.9915375],"iteration":134,"passed_time":1.883221439,"remaining_time":0.9067362485},
{"learn":[574.8649226],"iteration":135,"passed_time":1.895265746,"remaining_time":0.8918897628},
{"learn":[574.7939538],"iteration":136,"passed_time":1.906058831,"remaining_time":0.8765088057},
{"learn":[574.6000313],"iteration":137,"passed_time":1.919514133,"remaining_time":0.8623904077},
{"learn":[574.3756959],"iteration":138,"passed_time":1.931677359,"remaining_time":0.8477145244},
{"learn":[574.2591378],"iteration":139,"passed_time":1.942716977,"remaining_time":0.8325929899},
{"learn":[574.0290708],"iteration":140,"passed_time":1.954530876,"remaining_time":0.8178533452},
{"learn":[573.7905026],"iteration":141,"passed_time":1.966563797,"remaining_time":0.8032443678},
{"learn":[573.6203295],"iteration":142,"passed_time":1.978538867,"remaining_time":0.7886483596},
{"learn":[573.3589644],"iteration":143,"passed_time":1.991713855,"remaining_time":0.7745553881},
{"learn":[573.2194316],"iteration":144,"passed_time":2.003707192,"remaining_time":0.760026866},
{"learn":[573.099281],"iteration":145,"passed_time":2.015290114,"remaining_time":0.7453812751},
{"learn":[572.994668],"iteration":146,"passed_time":2.027277752,"remaining_time":0.730923271},
{"learn":[572.7850149],"iteration":147,"passed_time":2.040266086,"remaining_time":0.7168502465},
{"learn":[572.5712145],"iteration":148,"passed_time":2.052372977,"remaining_time":0.7024900793},
{"learn":[572.3467725],"iteration":149,"passed_time":2.065491813,"remaining_time":0.6884972711},
{"learn":[572.1287915],"iteration":150,"passed_time":2.080998444,"remaining_time":0.6752908857},
{"learn":[572.030676],"iteration":151,"passed_time":2.09741976,"remaining_time":0.662343082},
{"learn":[571.9159053],"iteration":152,"passed_time":2.114155343,"remaining_time":0.6494464125},
{"learn":[571.7905575],"iteration":153,"passed_time":2.129072093,"remaining_time":0.6359565993},
{"learn":[571.6583685],"iteration":154,"passed_time":2.146997359,"remaining_time":0.623321814},
{"learn":[571.5479338],"iteration":155,"passed_time":2.160207309,"remaining_time":0.6092892411},
{"learn":[571.3369343],"iteration":156,"passed_time":2.181699033,"remaining_time":0.5975354039},
{"learn":[571.1145252],"iteration":157,"passed_time":2.201123206,"remaining_time":0.5851087004},
{"learn":[570.8167226],"iteration":158,"passed_time":2.219135045,"remaining_time":0.5722297914},
{"learn":[570.6115984],"iteration":159,"passed_time":2.237622243,"remaining_time":0.5594055606},
{"learn":[570.4543586],"iteration":160,"passed_time":2.254665175,"remaining_time":0.5461611294},
{"learn":[570.3290534],"iteration":161,"passed_time":2.275800567,"remaining_time":0.5338297627},
{"learn":[570.1703067],"iteration":162,"passed_time":2.294023121,"remaining_time":0.5207291747},
{"learn":[570.0012139],"iteration":163,"passed_time":2.315263707,"remaining_time":0.5082286186},
{"learn":[569.8328667],"iteration":164,"passed_time":2.339507092,"remaining_time":0.4962590801},
{"learn":[569.6839721],"iteration":165,"passed_time":2.366468085,"remaining_time":0.4846982826},
{"learn":[569.5784058],"iteration":166,"passed_time":2.384532016,"remaining_time":0.4711949493},
{"learn":[569.4752729],"iteration":167,"passed_time":2.409710602,"remaining_time":0.4589924956},
{"learn":[569.3608332],"iteration":168,"passed_time":2.431794841,"remaining_time":0.4460688761},
{"learn":[569.2430285],"iteration":169,"passed_time":2.451548088,"remaining_time":0.4326261333},
{"learn":[569.1706957],"iteration":170,"passed_time":2.475309021,"remaining_time":0.4197892492},
{"learn":[569.0191791],"iteration":171,"passed_time":2.503792744,"remaining_time":0.4075941677},
{"learn":[568.9440522],"iteration":172,"passed_time":2.525359408,"remaining_time":0.3941312371},
{"learn":[568.8174703],"iteration":173,"passed_time":2.556060842,"remaining_time":0.3819401258},
{"learn":[568.6979754],"iteration":174,"passed_time":2.577758568,"remaining_time":0.3682512241},
{"learn":[568.5621629],"iteration":175,"passed_time":2.599410909,"remaining_time":0.354465124},
{"learn":[568.4509734],"iteration":176,"passed_time":2.620709097,"remaining_time":0.34054412},
{"learn":[568.3191725],"iteration":177,"passed_time":2.640088978,"remaining_time":0.3263031321},
{"learn":[568.1720852],"iteration":178,"passed_time":2.658865483,"remaining_time":0.3119339393},
{"learn":[568.0989464],"iteration":179,"passed_time":2.675453808,"remaining_time":0.2972726454},
{"learn":[567.9535339],"iteration":180,"passed_time":2.694053287,"remaining_time":0.2828011738},
{"learn":[567.8198332],"iteration":181,"passed_time":2.712107695,"remaining_time":0.2682304314},
{"learn":[567.7096453],"iteration":182,"passed_time":2.728118066,"remaining_time":0.2534317329},
{"learn":[567.6279501],"iteration":183,"passed_time":2.743921842,"remaining_time":0.2386018993},
{"learn":[567.5054099],"iteration":184,"passed_time":2.761002562,"remaining_time":0.2238650726},
{"learn":[567.3307465],"iteration":185,"passed_time":2.778179373,"remaining_time":0.2091102754},
{"learn":[567.3073309],"iteration":186,"passed_time":2.793408937,"remaining_time":0.1941942042},
{"learn":[567.0614935],"iteration":187,"passed_time":2.807694983,"remaining_time":0.1792145734},
{"learn":[566.9858046],"iteration":188,"passed_time":2.822226239,"remaining_time":0.1642565536},
{"learn":[566.8647233],"iteration":189,"passed_time":2.837775694,"remaining_time":0.1493566155},
{"learn":[566.7900901],"iteration":190,"passed_time":2.850280189,"remaining_time":0.1343063964},
{"learn":[566.6945139],"iteration":191,"passed_time":2.865955123,"remaining_time":0.1194147968},
{"learn":[566.5790487],"iteration":192,"passed_time":2.880822844,"remaining_time":0.1044858026},
{"learn":[566.387927],"iteration":193,"passed_time":2.893646677,"remaining_time":0.08949422714},
{"learn":[566.2663312],"iteration":194,"passed_time":2.90769815,"remaining_time":0.07455636283},
{"learn":[566.1311636],"iteration":195,"passed_time":2.921124622,"remaining_time":0.05961478821},
{"learn":[565.9951097],"iteration":196,"passed_time":2.935070645,"remaining_time":0.04469650729},
{"learn":[565.8767466],"iteration":197,"passed_time":2.950726998,"remaining_time":0.02980532321},
{"learn":[565.7607724],"iteration":198,"passed_time":2.964702817,"remaining_time":0.0148980041},
{"learn":[565.6559899],"iteration":199,"passed_time":2.977544371,"remaining_time":0}
]}